jaye/Jaye.py
jaye/__init__.py
jaye/applications.py
jaye/settings.py
jaye-0.0.13.dist-info/METADATA
jaye-0.0.13.dist-info/WHEEL
jaye-0.0.13.dist-info/top_level.txt
jaye-0.0.13.dist-info/RECORD
